sqterritory/__init__.py
sqterritory/__version__.py
sqterritory/territory.py
sqterritory-0.0.5.dist-info/LICENSE
sqterritory-0.0.5.dist-info/METADATA
sqterritory-0.0.5.dist-info/WHEEL
sqterritory-0.0.5.dist-info/top_level.txt
sqterritory-0.0.5.dist-info/RECORD
